LICENSE-others__.md
LICENSE-src-web3_app-chat__.md
MANIFEST.in
README.md
setup.py
src/web3_app/__init__.py
src/web3_app/gui.py
src/web3_app/web3_app.py
src/web3_app.egg-info/PKG-INFO
src/web3_app.egg-info/SOURCES.txt
src/web3_app.egg-info/dependency_links.txt
src/web3_app.egg-info/entry_points.txt
src/web3_app.egg-info/not-zip-safe
src/web3_app.egg-info/requires.txt
src/web3_app.egg-info/top_level.txt
src/web3_app/assets/favicon.png
src/web3_app/assets/icons/loading-animation.png
src/web3_app/chat/chat.py