Metadata-Version: 2.1
Name: web3-app
Version: 0.2.5
Summary: The source of Web3.
Home-page: https://github.com/Naruno/Web3_App
Author: Naruno Developers
Author-email: onur.atakan.ulusoy@naruno.org
License: MIT
Platform: UNKNOWN
Requires-Python: >= 3
